{
  "identifier": "com.greggerz.standardnotes-nord-theme",
  "name": "Nord Theme",
  "description": "A Nord theme for Standard Notes.",
  "content_type": "SN|Theme",
  "area": "themes",
  "version": "1.0.0",
  "main": "dist/nord-theme.css",
  "url": "https://cdn.jsdelivr.net/gh/greggerz/standardnotes-nord-theme@gh-pages/nord-theme.css",
  "download_url": "https://github.com/greggerz/standardnotes-nord-theme/archive/refs/tags/dist-v1.0.0.zip",
  "latest_url": "https://listed.to/p/rJPRlkSjml",
  "marketing_url": "https://github.com/greggerz/standardnotes-nord-theme",
  "dock_icon": {
    "type": "circle",
    "background_color": "#8FBCBB",
    "foreground_color": "#8FBCBB",
    "border_color": "#4C566A"
  }
}
